pyIVA/__init__.py
pyIVA-0.0.1.dist-info/LICENSE
pyIVA-0.0.1.dist-info/METADATA
pyIVA-0.0.1.dist-info/WHEEL
pyIVA-0.0.1.dist-info/top_level.txt
pyIVA-0.0.1.dist-info/RECORD
